apistar_peewee_orm/__init__.py
apistar_peewee_orm/__init__.py
apistar_peewee_orm/__main__.py
apistar_peewee_orm/__main__.py
apistar_peewee_orm/components.py
apistar_peewee_orm/components.py
apistar_peewee_orm/database.py
apistar_peewee_orm/database.py
apistar_peewee_orm/event_hooks.py
apistar_peewee_orm/event_hooks.py
apistar_peewee_orm/manager.py
apistar_peewee_orm/manager.py
apistar_peewee_orm-0.3.6.dist-info/entry_points.txt
apistar_peewee_orm-0.3.6.dist-info/LICENSE
apistar_peewee_orm-0.3.6.dist-info/WHEEL
apistar_peewee_orm-0.3.6.dist-info/METADATA
apistar_peewee_orm-0.3.6.dist-info/RECORD
