Metadata-Version: 2.1
Name: apistar-peewee-orm
Version: 0.3.6
Summary: Peewee integration for API Star.
Home-page: https://github.com/PeRDy/apistar-peewee-orm
License: GPL-3.0+
Keywords: apistar,peewee,orm
Author: José Antonio Perdiguero López
Author-email: perdy@perdy.io
Requires-Python: >=3.6,<4.0
Classifier: License :: OSI Approved :: GNU General Public License v3 or later (GPLv3+)
Classifier: Programming Language :: Python :: 3
Classifier: Programming Language :: Python :: 3.6
Classifier: Programming Language :: Python :: 3.7
Provides-Extra: apsw
Provides-Extra: mysql
Provides-Extra: postgresql
Requires-Dist: apistar (>=0.5.30,<0.6.0)
Requires-Dist: apsw (>=3.9,<4.0); extra == "apsw"
Requires-Dist: clinner (>=1.10,<2.0)
Requires-Dist: mysqlclient (>=1.3,<2.0); extra == "mysql"
Requires-Dist: peewee (>=3.5,<4.0)
Requires-Dist: peewee-migrate (>=1.0,<2.0)
Requires-Dist: psycopg2 (>=2.7,<3.0); extra == "postgresql"
